Metadata-Version: 1.1
Name: django-rest-secureview
Version: 0.0.4
Summary: Enforces client ViewSet requirements for Django Rest Framework
Home-page: https://github.com/fmitra/django-rest-secureview
Author: Francis Mitra
Author-email: francismitra@gmail.com
License: MIT
Download-URL: https://github.com/fmitra/django-rest-secureview/tarball/0.0.4
Keywords: django,django-restframework
Platform: UNKNOWN
